TensorBeliefFunction/__init__.py
TensorBeliefFunction/tensords.py
TensorBeliefFunction/tensords_csc.py
TensorBeliefFunction/tensords_csc_wise.py
TensorBeliefFunction/tensords_mask.py
TensorBeliefFunction/tensords_mask_csc.py
TensorBeliefFunction/test.py
tensorbelieffunction-0.0.8.dist-info/licenses/LICENSE
tensorbelieffunction-0.0.8.dist-info/METADATA
tensorbelieffunction-0.0.8.dist-info/WHEEL
tensorbelieffunction-0.0.8.dist-info/top_level.txt
tensorbelieffunction-0.0.8.dist-info/RECORD
