Metadata-Version: 2.4
Name: TensorBeliefFunction
Version: 0.0.8
Summary: Tensor of Belief Function
Home-page: https://github.com/nmtoan91/TensorBeliefFunction
Author: nmtoan91
Author-email: toan_stt@yahoo.com
Classifier: Programming Language :: Python :: 3
Classifier: License :: OSI Approved :: MIT License
Classifier: Operating System :: OS Independent
Requires-Python: >=3.6
License-File: LICENSE
Dynamic: author
Dynamic: author-email
Dynamic: classifier
Dynamic: description
Dynamic: description-content-type
Dynamic: home-page
Dynamic: license-file
Dynamic: requires-python
Dynamic: summary
